{
  "frame": {
    "version": "1",
    "name": "Delete Old Casts",
    "iconUrl": "https://delete-old-casts.vercel.app/logo.png",
    "homeUrl": "https://delete-old-casts.vercel.app",
    "imageUrl": "https://delete-old-casts.vercel.app/og.png",
    "buttonTitle": "🚩 Start",
    "splashImageUrl": "https://delete-old-casts.vercel.app/logo.png",
    "splashBackgroundColor": "#000000",
    "requiredChains": ["eip155:8453"],
    "requiredCapabilities": ["actions.signIn", "wallet.getEthereumProvider"]
  }
}
